chibi_github/__init__.py
chibi_github/chibi_github.py
chibi_github/cli.py
chibi_github/config.py
chibi_github/exception.py
chibi_github/response.py
chibi_github/serializers.py
chibi_github/urls.py
chibi_github-0.2.0.dist-info/licenses/AUTHORS.rst
chibi_github-0.2.0.dist-info/licenses/LICENSE
chibi_github-0.2.0.dist-info/METADATA
chibi_github-0.2.0.dist-info/WHEEL
chibi_github-0.2.0.dist-info/entry_points.txt
chibi_github-0.2.0.dist-info/top_level.txt
chibi_github-0.2.0.dist-info/RECORD
