Metadata-Version: 2.4
Name: chibi_github
Version: 0.2.0
Summary: libreria para usar github
Home-page: https://github.com/dem4ply/chibi_github
Author: dem4ply
Author-email: dem4ply@gmail.com
License: WTFPL
Keywords: chibi_github
Classifier: Development Status :: 2 - Pre-Alpha
Classifier: Intended Audience :: Developers
Classifier: License :: Public Domain
Classifier: Natural Language :: English
Classifier: Programming Language :: Python :: 3.7
Classifier: Programming Language :: Python :: 3.8
License-File: LICENSE
License-File: AUTHORS.rst
Requires-Dist: chibi_api>=0.1.0
Dynamic: author
Dynamic: author-email
Dynamic: classifier
Dynamic: description
Dynamic: home-page
Dynamic: keywords
Dynamic: license
Dynamic: license-file
Dynamic: requires-dist
Dynamic: summary
